bitcrypt/__init__.py
bitcrypt/crypt.py
bitcrypt-1.0.0.dist-info/METADATA
bitcrypt-1.0.0.dist-info/WHEEL
bitcrypt-1.0.0.dist-info/entry_points.txt
bitcrypt-1.0.0.dist-info/top_level.txt
bitcrypt-1.0.0.dist-info/RECORD
