Metadata-Version: 2.1
Name: bitcrypt
Version: 1.0.0
Summary: A library for bit-level encryption and decryption with Base64 encoding.
Author: AndrewCo
Classifier: Programming Language :: Python :: 3
Classifier: License :: OSI Approved :: MIT License
Classifier: Operating System :: OS Independent
Requires-Python: >=3.6
